pysimio/__init__.py
pysimio/api.py
pysimio/classes.py
pysimio/exceptions.py
pysimio/experiments.py
pysimio/logger.py
pysimio-1.9.0.dist-info/METADATA
pysimio-1.9.0.dist-info/WHEEL
pysimio-1.9.0.dist-info/licenses/LICENSE
pysimio-1.9.0.dist-info/RECORD
