Metadata-Version: 2.4
Name: pysimio
Version: 1.9.0
Summary: 
License: Apache Licesne 2.0
License-File: LICENSE
Author: Trevor Reed
Author-email: treed@simio.com
Requires-Python: >=3.9,<4.0
Classifier: License :: Other/Proprietary License
Classifier: Programming Language :: Python :: 3
Classifier: Programming Language :: Python :: 3.9
Classifier: Programming Language :: Python :: 3.10
Classifier: Programming Language :: Python :: 3.11
Classifier: Programming Language :: Python :: 3.12
Classifier: Programming Language :: Python :: 3.13
Classifier: Programming Language :: Python :: 3.14
Requires-Dist: decorator (>=5.1.1,<6.0.0)
Requires-Dist: http-exceptions (>=0.2.10,<0.3.0)
Requires-Dist: requests (>=2.32.3,<3.0.0)
Requires-Dist: tenacity (>=9.0.0,<10.0.0)
